mlnative/__init__.py
mlnative/_bridge.py
mlnative/_renderer.js
mlnative/exceptions.py
mlnative/map.py
mlnative/_vendor/darwin-arm64/package.json
mlnative/_vendor/darwin-x64/package.json
mlnative/_vendor/linux-arm64/bun.lock
mlnative/_vendor/linux-arm64/package.json
mlnative/_vendor/linux-x64/bun.lock
mlnative/_vendor/linux-x64/package.json
mlnative/_vendor/win32-x64/package.json
mlnative/bin/README.md
mlnative/bin/mlnative-render-linux-x64
mlnative-0.2.1.dist-info/METADATA
mlnative-0.2.1.dist-info/WHEEL
mlnative-0.2.1.dist-info/licenses/LICENSE
mlnative-0.2.1.dist-info/RECORD
