Metadata-Version: 2.4
Name: mlnative
Version: 0.2.1
Summary: Simple Python wrapper for MapLibre GL Native using native Rust renderer
Project-URL: Homepage, https://github.com/adonm/mlnative
Project-URL: Repository, https://github.com/adonm/mlnative
Project-URL: Issues, https://github.com/adonm/mlnative/issues
Author: Adon Metcalfe
License: Apache-2.0
License-File: LICENSE
Keywords: maplibre,maps,rendering,static-maps,tiles
Classifier: Development Status :: 3 - Alpha
Classifier: Intended Audience :: Developers
Classifier: License :: OSI Approved :: Apache Software License
Classifier: Programming Language :: Python :: 3
Classifier: Programming Language :: Python :: 3.12
Classifier: Programming Language :: Python :: 3.13
Classifier: Programming Language :: Rust
Classifier: Topic :: Scientific/Engineering :: GIS
Requires-Python: >=3.12
Provides-Extra: dev
Requires-Dist: cibuildwheel>=2.16; extra == 'dev'
Requires-Dist: httpx>=0.27; extra == 'dev'
Requires-Dist: mypy>=1.13.0; extra == 'dev'
Requires-Dist: pytest>=8.0; extra == 'dev'
Requires-Dist: ruff>=0.8.0; extra == 'dev'
Provides-Extra: web
Requires-Dist: fastapi>=0.115; extra == 'web'
Requires-Dist: jinja2>=3.1; extra == 'web'
Requires-Dist: python-multipart>=0.0.20; extra == 'web'
Requires-Dist: uvicorn[standard]>=0.32; extra == 'web'
